{"nodes": [{"id": "d_projects_ai_trader_auth_src_controllers_billing_controller_js", "label": "billing.controller.js", "file_type": "code", "source_file": "D:\\projects\\Ai-trader\\auth\\src\\controllers\\billing.controller.js", "source_location": "L1"}, {"id": "controllers_billing_controller_billingcontroller", "label": "BillingController", "file_type": "code", "source_file": "D:\\projects\\Ai-trader\\auth\\src\\controllers\\billing.controller.js", "source_location": "L8"}, {"id": "controllers_billing_controller_billingcontroller_getplans", "label": ".getPlans()", "file_type": "code", "source_file": "D:\\projects\\Ai-trader\\auth\\src\\controllers\\billing.controller.js", "source_location": "L13"}, {"id": "controllers_billing_controller_billingcontroller_createcheckout", "label": ".createCheckout()", "file_type": "code", "source_file": "D:\\projects\\Ai-trader\\auth\\src\\controllers\\billing.controller.js", "source_location": "L34"}, {"id": "controllers_billing_controller_billingcontroller_transitionsubscription", "label": ".transitionSubscription()", "file_type": "code", "source_file": "D:\\projects\\Ai-trader\\auth\\src\\controllers\\billing.controller.js", "source_location": "L80"}], "edges": [{"source": "d_projects_ai_trader_auth_src_controllers_billing_controller_js", "target": "d_projects_ai_trader_auth_src_services_billing_service_ts", "relation": "imports_from", "context": "import", "confidence": "EXTRACTED", "source_file": "D:\\projects\\Ai-trader\\auth\\src\\controllers\\billing.controller.js", "source_location": "L6", "weight": 1.0}, {"source": "d_projects_ai_trader_auth_src_controllers_billing_controller_js", "target": "services_billing_service_billingservice", "relation": "imports", "context": "import", "confidence": "EXTRACTED", "source_file": "D:\\projects\\Ai-trader\\auth\\src\\controllers\\billing.controller.js", "source_location": "L6", "weight": 1.0}, {"source": "d_projects_ai_trader_auth_src_controllers_billing_controller_js", "target": "controllers_billing_controller_billingcontroller", "relation": "contains", "confidence": "EXTRACTED", "source_file": "D:\\projects\\Ai-trader\\auth\\src\\controllers\\billing.controller.js", "source_location": "L8", "weight": 1.0}, {"source": "controllers_billing_controller_billingcontroller", "target": "controllers_billing_controller_billingcontroller_getplans", "relation": "method", "confidence": "EXTRACTED", "source_file": "D:\\projects\\Ai-trader\\auth\\src\\controllers\\billing.controller.js", "source_location": "L13", "weight": 1.0}, {"source": "controllers_billing_controller_billingcontroller", "target": "controllers_billing_controller_billingcontroller_createcheckout", "relation": "method", "confidence": "EXTRACTED", "source_file": "D:\\projects\\Ai-trader\\auth\\src\\controllers\\billing.controller.js", "source_location": "L34", "weight": 1.0}, {"source": "controllers_billing_controller_billingcontroller", "target": "controllers_billing_controller_billingcontroller_transitionsubscription", "relation": "method", "confidence": "EXTRACTED", "source_file": "D:\\projects\\Ai-trader\\auth\\src\\controllers\\billing.controller.js", "source_location": "L80", "weight": 1.0}], "raw_calls": [{"caller_nid": "controllers_billing_controller_billingcontroller_getplans", "callee": "send", "is_member_call": true, "source_file": "D:\\projects\\Ai-trader\\auth\\src\\controllers\\billing.controller.js", "source_location": "L16"}, {"caller_nid": "controllers_billing_controller_billingcontroller_getplans", "callee": "error", "is_member_call": true, "source_file": "D:\\projects\\Ai-trader\\auth\\src\\controllers\\billing.controller.js", "source_location": "L21"}, {"caller_nid": "controllers_billing_controller_billingcontroller_getplans", "callee": "send", "is_member_call": true, "source_file": "D:\\projects\\Ai-trader\\auth\\src\\controllers\\billing.controller.js", "source_location": "L22"}, {"caller_nid": "controllers_billing_controller_billingcontroller_getplans", "callee": "status", "is_member_call": true, "source_file": "D:\\projects\\Ai-trader\\auth\\src\\controllers\\billing.controller.js", "source_location": "L22"}, {"caller_nid": "controllers_billing_controller_billingcontroller_createcheckout", "callee": "send", "is_member_call": true, "source_file": "D:\\projects\\Ai-trader\\auth\\src\\controllers\\billing.controller.js", "source_location": "L40"}, {"caller_nid": "controllers_billing_controller_billingcontroller_createcheckout", "callee": "status", "is_member_call": true, "source_file": "D:\\projects\\Ai-trader\\auth\\src\\controllers\\billing.controller.js", "source_location": "L40"}, {"caller_nid": "controllers_billing_controller_billingcontroller_createcheckout", "callee": "createCheckoutSession", "is_member_call": true, "source_file": "D:\\projects\\Ai-trader\\auth\\src\\controllers\\billing.controller.js", "source_location": "L46"}, {"caller_nid": "controllers_billing_controller_billingcontroller_createcheckout", "callee": "send", "is_member_call": true, "source_file": "D:\\projects\\Ai-trader\\auth\\src\\controllers\\billing.controller.js", "source_location": "L48"}, {"caller_nid": "controllers_billing_controller_billingcontroller_createcheckout", "callee": "error", "is_member_call": true, "source_file": "D:\\projects\\Ai-trader\\auth\\src\\controllers\\billing.controller.js", "source_location": "L55"}, {"caller_nid": "controllers_billing_controller_billingcontroller_createcheckout", "callee": "includes", "is_member_call": true, "source_file": "D:\\projects\\Ai-trader\\auth\\src\\controllers\\billing.controller.js", "source_location": "L56"}, {"caller_nid": "controllers_billing_controller_billingcontroller_createcheckout", "callee": "send", "is_member_call": true, "source_file": "D:\\projects\\Ai-trader\\auth\\src\\controllers\\billing.controller.js", "source_location": "L57"}, {"caller_nid": "controllers_billing_controller_billingcontroller_createcheckout", "callee": "status", "is_member_call": true, "source_file": "D:\\projects\\Ai-trader\\auth\\src\\controllers\\billing.controller.js", "source_location": "L57"}, {"caller_nid": "controllers_billing_controller_billingcontroller_createcheckout", "callee": "includes", "is_member_call": true, "source_file": "D:\\projects\\Ai-trader\\auth\\src\\controllers\\billing.controller.js", "source_location": "L62"}, {"caller_nid": "controllers_billing_controller_billingcontroller_createcheckout", "callee": "send", "is_member_call": true, "source_file": "D:\\projects\\Ai-trader\\auth\\src\\controllers\\billing.controller.js", "source_location": "L63"}, {"caller_nid": "controllers_billing_controller_billingcontroller_createcheckout", "callee": "status", "is_member_call": true, "source_file": "D:\\projects\\Ai-trader\\auth\\src\\controllers\\billing.controller.js", "source_location": "L63"}, {"caller_nid": "controllers_billing_controller_billingcontroller_createcheckout", "callee": "send", "is_member_call": true, "source_file": "D:\\projects\\Ai-trader\\auth\\src\\controllers\\billing.controller.js", "source_location": "L68"}, {"caller_nid": "controllers_billing_controller_billingcontroller_createcheckout", "callee": "status", "is_member_call": true, "source_file": "D:\\projects\\Ai-trader\\auth\\src\\controllers\\billing.controller.js", "source_location": "L68"}, {"caller_nid": "controllers_billing_controller_billingcontroller_transitionsubscription", "callee": "send", "is_member_call": true, "source_file": "D:\\projects\\Ai-trader\\auth\\src\\controllers\\billing.controller.js", "source_location": "L86"}, {"caller_nid": "controllers_billing_controller_billingcontroller_transitionsubscription", "callee": "status", "is_member_call": true, "source_file": "D:\\projects\\Ai-trader\\auth\\src\\controllers\\billing.controller.js", "source_location": "L86"}, {"caller_nid": "controllers_billing_controller_billingcontroller_transitionsubscription", "callee": "send", "is_member_call": true, "source_file": "D:\\projects\\Ai-trader\\auth\\src\\controllers\\billing.controller.js", "source_location": "L94"}, {"caller_nid": "controllers_billing_controller_billingcontroller_transitionsubscription", "callee": "error", "is_member_call": true, "source_file": "D:\\projects\\Ai-trader\\auth\\src\\controllers\\billing.controller.js", "source_location": "L99"}, {"caller_nid": "controllers_billing_controller_billingcontroller_transitionsubscription", "callee": "includes", "is_member_call": true, "source_file": "D:\\projects\\Ai-trader\\auth\\src\\controllers\\billing.controller.js", "source_location": "L100"}, {"caller_nid": "controllers_billing_controller_billingcontroller_transitionsubscription", "callee": "includes", "is_member_call": true, "source_file": "D:\\projects\\Ai-trader\\auth\\src\\controllers\\billing.controller.js", "source_location": "L100"}, {"caller_nid": "controllers_billing_controller_billingcontroller_transitionsubscription", "callee": "send", "is_member_call": true, "source_file": "D:\\projects\\Ai-trader\\auth\\src\\controllers\\billing.controller.js", "source_location": "L101"}, {"caller_nid": "controllers_billing_controller_billingcontroller_transitionsubscription", "callee": "status", "is_member_call": true, "source_file": "D:\\projects\\Ai-trader\\auth\\src\\controllers\\billing.controller.js", "source_location": "L101"}, {"caller_nid": "controllers_billing_controller_billingcontroller_transitionsubscription", "callee": "includes", "is_member_call": true, "source_file": "D:\\projects\\Ai-trader\\auth\\src\\controllers\\billing.controller.js", "source_location": "L106"}, {"caller_nid": "controllers_billing_controller_billingcontroller_transitionsubscription", "callee": "send", "is_member_call": true, "source_file": "D:\\projects\\Ai-trader\\auth\\src\\controllers\\billing.controller.js", "source_location": "L107"}, {"caller_nid": "controllers_billing_controller_billingcontroller_transitionsubscription", "callee": "status", "is_member_call": true, "source_file": "D:\\projects\\Ai-trader\\auth\\src\\controllers\\billing.controller.js", "source_location": "L107"}, {"caller_nid": "controllers_billing_controller_billingcontroller_transitionsubscription", "callee": "send", "is_member_call": true, "source_file": "D:\\projects\\Ai-trader\\auth\\src\\controllers\\billing.controller.js", "source_location": "L112"}, {"caller_nid": "controllers_billing_controller_billingcontroller_transitionsubscription", "callee": "status", "is_member_call": true, "source_file": "D:\\projects\\Ai-trader\\auth\\src\\controllers\\billing.controller.js", "source_location": "L112"}]}