{"nodes": [{"id": "d_projects_ai_trader_frontend_tests_e2e_spec_ts", "label": "e2e.spec.ts", "file_type": "code", "source_file": "D:\\projects\\Ai-trader\\frontend\\tests\\e2e.spec.ts", "source_location": "L1"}, {"id": "tests_e2e_spec_setupmockroutes", "label": "setupMockRoutes()", "file_type": "code", "source_file": "D:\\projects\\Ai-trader\\frontend\\tests\\e2e.spec.ts", "source_location": "L56"}, {"id": "tests_e2e_spec_attachipcmonitors", "label": "attachIpcMonitors()", "file_type": "code", "source_file": "D:\\projects\\Ai-trader\\frontend\\tests\\e2e.spec.ts", "source_location": "L67"}, {"id": "tests_e2e_spec_invoke", "label": "invoke()", "file_type": "code", "source_file": "D:\\projects\\Ai-trader\\frontend\\tests\\e2e.spec.ts", "source_location": "L161"}], "edges": [{"source": "d_projects_ai_trader_frontend_tests_e2e_spec_ts", "target": "test", "relation": "imports_from", "context": "import", "confidence": "EXTRACTED", "source_file": "D:\\projects\\Ai-trader\\frontend\\tests\\e2e.spec.ts", "source_location": "L23", "weight": 1.0}, {"source": "d_projects_ai_trader_frontend_tests_e2e_spec_ts", "target": "tests_e2e_spec_setupmockroutes", "relation": "contains", "confidence": "EXTRACTED", "source_file": "D:\\projects\\Ai-trader\\frontend\\tests\\e2e.spec.ts", "source_location": "L56", "weight": 1.0}, {"source": "d_projects_ai_trader_frontend_tests_e2e_spec_ts", "target": "tests_e2e_spec_attachipcmonitors", "relation": "contains", "confidence": "EXTRACTED", "source_file": "D:\\projects\\Ai-trader\\frontend\\tests\\e2e.spec.ts", "source_location": "L67", "weight": 1.0}, {"source": "d_projects_ai_trader_frontend_tests_e2e_spec_ts", "target": "tests_e2e_spec_invoke", "relation": "contains", "confidence": "EXTRACTED", "source_file": "D:\\projects\\Ai-trader\\frontend\\tests\\e2e.spec.ts", "source_location": "L161", "weight": 1.0}], "raw_calls": [{"caller_nid": "tests_e2e_spec_setupmockroutes", "callee": "route", "is_member_call": true, "source_file": "D:\\projects\\Ai-trader\\frontend\\tests\\e2e.spec.ts", "source_location": "L57"}, {"caller_nid": "tests_e2e_spec_attachipcmonitors", "callee": "on", "is_member_call": true, "source_file": "D:\\projects\\Ai-trader\\frontend\\tests\\e2e.spec.ts", "source_location": "L68"}, {"caller_nid": "tests_e2e_spec_attachipcmonitors", "callee": "on", "is_member_call": true, "source_file": "D:\\projects\\Ai-trader\\frontend\\tests\\e2e.spec.ts", "source_location": "L71"}, {"caller_nid": "tests_e2e_spec_attachipcmonitors", "callee": "on", "is_member_call": true, "source_file": "D:\\projects\\Ai-trader\\frontend\\tests\\e2e.spec.ts", "source_location": "L74"}, {"caller_nid": "tests_e2e_spec_invoke", "callee": "handler", "is_member_call": false, "source_file": "D:\\projects\\Ai-trader\\frontend\\tests\\e2e.spec.ts", "source_location": "L164"}]}